<?xml version="1.0" encoding="utf-8" ?>
<dwsync>
<file name="background.png" server="94.136.62.229/httpdocs/" local="129114530400000000" remote="129114530400000000" />
<file name="chameleon.info" server="94.136.62.229/httpdocs/" local="129114530400000000" remote="129114530400000000" />
<file name="chameleon.theme" server="94.136.62.229/httpdocs/" local="129114530400000000" remote="129114530400000000" />
<file name="common-rtl.css" server="94.136.62.229/httpdocs/" local="129114530400000000" remote="129114530400000000" />
<file name="common.css" server="94.136.62.229/httpdocs/" local="129114530400000000" remote="129114530400000000" />
<file name="logo.png" server="94.136.62.229/httpdocs/" local="129114530400000000" remote="129114530400000000" />
<file name="screenshot.png" server="94.136.62.229/httpdocs/" local="129114530400000000" remote="129114530400000000" />
<file name="style-rtl.css" server="94.136.62.229/httpdocs/" local="129114530400000000" remote="129114530400000000" />
<file name="style.css" server="94.136.62.229/httpdocs/" local="129114530400000000" remote="129114530400000000" />
</dwsync>